aut/__init__.py
aut/py.typed
aut-0.0.1.dist-info/METADATA
aut-0.0.1.dist-info/WHEEL
aut-0.0.1.dist-info/licenses/LICENSE
aut-0.0.1.dist-info/RECORD
