Metadata-Version: 2.4
Name: aut
Version: 0.0.1
Summary: Authentication, simplified.
Project-URL: Documentation, https://frankie567.github.io/aut/
Project-URL: Source, https://github.com/frankie567/aut
Author-email: aut <aut@francoisvoron.com>
License-File: LICENSE
Classifier: Programming Language :: Python :: 3 :: Only
Classifier: Programming Language :: Python :: 3.13
Requires-Python: >=3.13
Requires-Dist: anyio
